setup.py
MongoPhile.egg-info/PKG-INFO
MongoPhile.egg-info/SOURCES.txt
MongoPhile.egg-info/dependency_links.txt
MongoPhile.egg-info/entry_points.txt
MongoPhile.egg-info/top_level.txt
mongophile/__init__.py
mongophile/ops.py
mongophile/parser.py