Metadata-Version: 1.0
Name: MongoPhile
Version: 0.1.0
Summary: Parse utilities for the MongoDB Profiler log
Home-page: http://github.com/bwmcadams/mongophile
Author: Brendan W. McAdams
Author-email: brendan@10gen.com
License: UNKNOWN
Platform: UNKNOWN
